dashboard_pkg/__init__.py
dashboard_pkg/dashboard.py
tests/__init__.py
airportstaff_dashboard-0.1.0.dist-info/LICENSE
airportstaff_dashboard-0.1.0.dist-info/METADATA
airportstaff_dashboard-0.1.0.dist-info/WHEEL
airportstaff_dashboard-0.1.0.dist-info/top_level.txt
airportstaff_dashboard-0.1.0.dist-info/RECORD
