Metadata-Version: 2.1
Name: airportstaff-dashboard
Version: 0.1.0
Summary: Simple library for listing/managing airport staff dashboards
Home-page: https://github.com/Comrade-Glitch-cloud/airportstaff_daashboard-Library
Author: Benny Geddam
Author-email: geddambenny55@gmail.com
License: UNKNOWN
Platform: UNKNOWN
Classifier: Programming Language :: Python :: 3
Classifier: License :: OSI Approved :: MIT License
Classifier: Operating System :: OS Independent
Requires-Python: >=3.6
License-File: LICENSE
